file_manager_integration/__init__.py
file_manager_integration/__main__.py
file_manager_integration/cli.py
file_manager_integration/dialog.py
file_manager_integration/file_managers.py
file_manager_integration-0.2.2.dist-info/LICENSE
file_manager_integration-0.2.2.dist-info/METADATA
file_manager_integration-0.2.2.dist-info/WHEEL
file_manager_integration-0.2.2.dist-info/entry_points.txt
file_manager_integration-0.2.2.dist-info/top_level.txt
file_manager_integration-0.2.2.dist-info/RECORD
