Metadata-Version: 2.1
Name: file-manager-integration
Version: 0.2.2
Summary: Integration of scripts into various Unix file managers
Home-page: https://github.com/blackstream-x/file-manager-integration
Author: Rainer Schwarzbach
Author-email: undisclosed@example.com
License: UNKNOWN
Project-URL: Documentation, https://github.com/blackstream-x/file-manager-integration
Project-URL: Source, https://github.com/blackstream-x/file-manager-integration
Project-URL: Tracker, https://github.com/blackstream-x/file-manager-integration/issues
Platform: UNKNOWN
Classifier: Development Status :: 4 - Beta
Classifier: License :: OSI Approved :: GNU General Public License v3 or later (GPLv3+)
Classifier: Intended Audience :: End Users/Desktop
Classifier: Topic :: Desktop Environment :: File Managers
Classifier: Operating System :: POSIX
Classifier: Environment :: Console
Classifier: Programming Language :: Python :: 3
Classifier: Programming Language :: Python :: 3.6
Classifier: Programming Language :: Python :: 3.7
Classifier: Programming Language :: Python :: 3.8
Classifier: Programming Language :: Python :: 3.9
Classifier: Programming Language :: Python :: 3.10
Classifier: Programming Language :: Python :: 3 :: Only
Requires-Python: >=3.6
License-File: LICENSE
